redirectto/__init__.py
redirectto-0.0.2.data/scripts/redirect-to
redirectto-0.0.2.dist-info/LICENSE
redirectto-0.0.2.dist-info/METADATA
redirectto-0.0.2.dist-info/WHEEL
redirectto-0.0.2.dist-info/top_level.txt
redirectto-0.0.2.dist-info/zip-safe
redirectto-0.0.2.dist-info/RECORD
